{"ignoreUnknownInstances":true,"className":"LocalizationTable","properties":{"SourceLocaleId":"en-us","Contents":"[{\"key\":\"Studio.ConstraintTool.Plugin.Name\",\"source\":\"Attachment Tool\",\"values\":{\"pt-br\":\"Ferramenta de anexos\",\"tr-tr\":\"Eklenti Aracı\",\"zh-tw\":\"附件工具\",\"vi-vn\":\"Công Cụ Đính Kèm\",\"es-es\":\"Herramienta de conexión\",\"ja-jp\":\"アタッチメントツール\",\"fr-fr\":\"Outil points d'attache\",\"ko-kr\":\"연결부 도구\",\"th-th\":\"เครื่องมือจุดเชื่อมต่อ\",\"en-us\":\"Attachment Tool\",\"de-de\":\"Anhangstool\",\"id-id\":\"Alat Sambungan\",\"it-it\":\"Strumento di attachment\",\"pl-pl\":\"Narzędzie do obsługi punktów zaczepienia\"}},{\"key\":\"Studio.ConstraintTool.Plugin.Toolbar\",\"source\":\"Attachment Tool\",\"values\":{\"pt-br\":\"Ferramenta de anexos\",\"tr-tr\":\"Eklenti Aracı\",\"zh-tw\":\"附件工具\",\"vi-vn\":\"Công Cụ Đính Kèm\",\"es-es\":\"Herramienta de conexión\",\"ja-jp\":\"アタッチメントツール\",\"fr-fr\":\"Outil de fixation\",\"ko-kr\":\"연결부 도구\",\"th-th\":\"เครื่องมือจุดเชื่อมต่อ\",\"en-us\":\"Attachment Tool\",\"de-de\":\"Anhangstool\",\"id-id\":\"Alat Sambungan\",\"it-it\":\"Strumento di attachment\",\"pl-pl\":\"Narzędzie do obsługi punktów zaczepienia\"}},{\"key\":\"Studio.ConstraintTool.Plugin.Description\",\"source\":\"Create an Attachment.\",\"values\":{\"pt-br\":\"Criar um anexo.\",\"tr-tr\":\"Eklenti oluştur.\",\"zh-tw\":\"建立附件。\",\"vi-vn\":\"Tạo Đính Kèm.\",\"es-es\":\"Crea una conexión.\",\"ja-jp\":\"アタッチメントを作成。\",\"fr-fr\":\"Créer un point d'attache.\",\"ko-kr\":\"연결부를 생성하세요.\",\"th-th\":\"สร้างจุดเชื่อมต่อ\",\"en-us\":\"Create an Attachment.\",\"de-de\":\"Erstelle einen Anhang.\",\"id-id\":\"Buat Sambungan.\",\"it-it\":\"Crea un allegato.\",\"pl-pl\":\"Utwórz punkt zaczepienia.\"}},{\"key\":\"Studio.ConstraintTool.Plugin.Button\",\"source\":\"Create\",\"values\":{\"pt-br\":\"Criar\",\"tr-tr\":\"Oluştur\",\"zh-tw\":\"建立\",\"vi-vn\":\"Tạo\",\"es-es\":\"Crear\",\"ja-jp\":\"作成\",\"fr-fr\":\"Créer\",\"ko-kr\":\"생성\",\"th-th\":\"สร้าง\",\"en-us\":\"Create\",\"de-de\":\"Erstellen\",\"id-id\":\"Buat\",\"it-it\":\"Crea\",\"pl-pl\":\"Utwórz\"}}]","SourceAssetId":-1,"DefinesCapabilities":false}}